migratore/__init__.py
migratore/__main__.py
migratore/base.py
migratore/cli.py
migratore/info.py
migratore/loader.py
migratore/migration.py
migratore/mysql.py
migratore/examples/__init__.py
migratore/examples/base.py
migratore/examples/migrations/1391804600.py
migratore/examples/migrations/1391804700.py
migratore/examples/migrations/1392032961.py
migratore/examples/migrations/__init__.py
migratore/templates/migration.py.tpl
migratore-0.6.0.dist-info/METADATA
migratore-0.6.0.dist-info/WHEEL
migratore-0.6.0.dist-info/entry_points.txt
migratore-0.6.0.dist-info/top_level.txt
migratore-0.6.0.dist-info/zip-safe
migratore-0.6.0.dist-info/RECORD
